bcm/LAYOUT.md
bcm/RECOMMENDATIONS.md
bcm/__init__.py
bcm/alt_layout.py
bcm/app.py
bcm/archimate_export.py
bcm/audit_view.py
bcm/business_capability_model.ico
bcm/database.py
bcm/dialogs.py
bcm/hq_layout.py
bcm/html_export.py
bcm/io.py
bcm/layout.py
bcm/layout_manager.py
bcm/markdown_export.py
bcm/mermaid_export.py
bcm/models.py
bcm/pb.py
bcm/plantuml_export.py
bcm/pptx_export.py
bcm/pydanticai.md
bcm/settings.py
bcm/squarecap-layout.html
bcm/svg_export.py
bcm/treeview.py
bcm/ui.py
bcm/utils.py
bcm/visualizer.py
bcm/web_agent.py
bcm/word_export.py
bcm/api/export_handler.py
bcm/api/server.py
bcm/static/assistant_avatar.png
bcm/static/chat.js
bcm/static/favicon.png
bcm/static/styles.css
bcm/static/user_avatar.png
bcm/static/client/vite.svg
bcm/templates/chat.html
bcm/templates/concept_expansion_prompt.j2
bcm/templates/expansion_prompt.j2
bcm/templates/expansion_prompt_gpt.j2
bcm/templates/first_level_concepts.j2
bcm/templates/first_level_prompt.j2
bcm/templates/first_level_prompt_gpt.j2
bcm/templates/system_prompt.j2
pybcm-0.1.14.dist-info/METADATA
pybcm-0.1.14.dist-info/WHEEL
pybcm-0.1.14.dist-info/entry_points.txt
pybcm-0.1.14.dist-info/licenses/LICENSE
pybcm-0.1.14.dist-info/RECORD
