Metadata-Version: 2.4
Name: pybcm
Version: 0.1.14
Summary: A Business Capability Modeler built with Python and ttkbootstrap
Project-URL: GitHub, https://github.com/ThomasRohde/PyBCM
Author-email: Thomas Klok Rohde <thomas@rohde.name>
License: MIT License
License-File: LICENSE
Keywords: bcm,business,capability,enterprise-architecture,modeling
Classifier: Development Status :: 4 - Beta
Classifier: Framework :: AsyncIO
Classifier: Framework :: FastAPI
Classifier: Intended Audience :: Developers
Classifier: Intended Audience :: Information Technology
Classifier: License :: OSI Approved :: MIT License
Classifier: Natural Language :: English
Classifier: Operating System :: OS Independent
Classifier: Programming Language :: Python :: 3
Classifier: Programming Language :: Python :: 3.13
Classifier: Topic :: Office/Business
Classifier: Topic :: Software Development :: Libraries :: Python Modules
Classifier: Topic :: Software Development :: User Interfaces
Requires-Python: >=3.11
Requires-Dist: aiosqlite>=0.20.0
Requires-Dist: fastapi>=0.115.6
Requires-Dist: greenlet>=3.1.1
Requires-Dist: jinja2>=3.1.5
Requires-Dist: json-repair>=0.35.0
Requires-Dist: logfire[sqlite3]>=2.11.0
Requires-Dist: markdown>=3.7
Requires-Dist: openpyxl>=3.1.5
Requires-Dist: pandas>=2.2.3
Requires-Dist: pydantic-ai[logfire]>=0.0.15
Requires-Dist: pydantic>=2.0.0
Requires-Dist: pyperclip>=1.9.0
Requires-Dist: python-docx>=1.1.2
Requires-Dist: python-dotenv>=1.0.1
Requires-Dist: python-pptx>=1.0.2
Requires-Dist: setuptools>=75.6.0
Requires-Dist: sqlalchemy>=2.0.0
Requires-Dist: tkhtmlview>=0.3.1
Requires-Dist: tkinterweb>=3.24.8
Requires-Dist: ttkbootstrap>=1.10.1
Requires-Dist: uvicorn[standard]>=0.34.0
